hocr_spec/__init__.py
hocr_spec/cli.py
hocr_spec/spec.py
hocr_spec/validate.py
hocr_spec-0.2.0.dist-info/AUTHORS
hocr_spec-0.2.0.dist-info/LICENSE
hocr_spec-0.2.0.dist-info/METADATA
hocr_spec-0.2.0.dist-info/WHEEL
hocr_spec-0.2.0.dist-info/entry_points.txt
hocr_spec-0.2.0.dist-info/pbr.json
hocr_spec-0.2.0.dist-info/top_level.txt
hocr_spec-0.2.0.dist-info/RECORD
